Workbook

Sheet Registration
A1: registration_number | B1: commercial_name | C1: common_name | D1: concentration | E1: formula_type | F1: origin | G1: applicant | H1: importer | I1: distributor | J1: issue_date | K1: expiry_date | L1: category | M1: moa_group
A2: 3 - 2554 | B2: เรนโบว 2.5 โอดี (Rainbow 2.5 OD) | C2: penoxsulam | D2: 2.5%W/V | E2: OD | F2: PT. Corteva Agriscience Manufacturing Indonesia, Indonesia | G2: ดาว อะโกรไซแอนส์ (ประเทศไทย) บจก. | H2: ดาว อะโกรไซแอนส์ (ประเทศไทย) บจก. | I2: คอร์เทวา อะกริไซเอนซ์ (ประเทศไทย) บจก. | J2: 07/04/2023 | K2: 06/04/2029 | L2: =IFERROR(_xlfn.XLOOKUP($C2,'Pesticide Types'!$A$2:$A$519,'Pesticide Types'!$B$2:$B$519),"Unclassified") -> Herbicide | M2: =IFERROR(_xlfn.XLOOKUP($C2,'Pesticide Types'!$A$2:$A$519,'Pesticide Types'!$D$2:$D$519),"None") -> HRAC 2
A3: 7 - 2554 | B3: พรีวาธอน (Prevathon) | C3: chlorantraniliprole | D3: 5.17%W/V | E3: SC | F3: FMC Agro Singapore Pte. Ltd., Singapore; FMC Vietnam Company Limited, Vietnam; PT FMC Agricultural Manufacturing, Indonesia; PT Bina Guna Kimia, Indonesia; Cheminova Deutschland GmbH & Co. KG, Germany | G3: เอฟเอ็ม ซี เอจี (ประเทศไทย) | H3: เอฟเอ็ม ซี เอจี (ประเทศไทย) | I3: เอฟเอ็ม ซี เอจี (ประเทศไทย) บจก. | J3: 07/04/2023 | K3: 06/04/2029 | L3: =IFERROR(_xlfn.XLOOKUP($C3,'Pesticide Types'!$A$2:$A$519,'Pesticide Types'!$B$2:$B$519),"Unclassified") -> Insecticide | M3: =IFERROR(_xlfn.XLOOKUP($C3,'Pesticide Types'!$A$2:$A$519,'Pesticide Types'!$D$2:$D$519),"None") -> IRAC 28
A4: 8 - 2554 | B4: อิมแพค (Impact) | C4: flutriafol | D4: 12.5%W/V | E4: SC | F4: FMC Quimica do Brasil Ltda., Brazil | G4: โซตัส อินเตอร์เนชั่นแนล บจก. | H4: โซตัส อินเตอร์เนชั่นแนล บจก. | I4: โซตัส อินเตอร์เนชั่นแนล บจก. | J4: 07/04/2023 | K4: 06/04/2029 | L4: =IFERROR(_xlfn.XLOOKUP($C4,'Pesticide Types'!$A$2:$A$519,'Pesticide Types'!$B$2:$B$519),"Unclassified") -> Fungicide | M4: =IFERROR(_xlfn.XLOOKUP($C4,'Pesticide Types'!$A$2:$A$519,'Pesticide Types'!$D$2:$D$519),"None") -> FRAC 3
A5: 9 - 2554 | B5: แอคเซ็บท์ 60 โอดี (Accept 60 OD) | C5: cyhalofop-butyl+penoxsulam | D5: 5%+1%W/V | E5: OD | F5: PT. Corteva Agriscience Manufacturing Indonesia, Indonesia | G5: คอร์เทวา อะกริไซเอนซ์ (ประเทศไทย) บจก. | H5: คอร์เทวา อะกริไซเอนซ์ (ประเทศไทย) บจก. | I5: คอร์เทวา อะกริไซเอนซ์ (ประเทศไทย) บจก. | J5: 20/04/2023 | K5: 19/04/2029 | L5: =IFERROR(_xlfn.XLOOKUP($C5,'Pesticide Types'!$A$2:$A$519,'Pesticide Types'!$B$2:$B$519),"Unclassified") -> Unclassified | M5: =IFERROR(_xlfn.XLOOKUP($C5,'Pesticide Types'!$A$2:$A$519,'Pesticide Types'!$D$2:$D$519),"None") -> None
A6: 10 - 2554 | B6: ดูอัล โกลด์ (Dual Gold) | C6: s-metolachlor | D6: 96%W/V | E6: EC | F6: Syngenta Production France S.A.S., France; Chemark ZRT., Hungary; Syngenta (Suzhou) Crop Protection Co., Ltd. PRC | G6: ซินเจนทา ครอป โปรเทคชั่น บจก. | H6: ซินเจนทา ครอป โปรเทคชั่น บจก. | I6: ซินเจนทา ครอป โปรเทคชั่น บจก. | J6: 02/05/2023 | K6: 01/05/2029 | L6: =IFERROR(_xlfn.XLOOKUP($C6,'Pesticide Types'!$A$2:$A$519,'Pesticide Types'!$B$2:$B$519),"Unclassified") -> Herbicide | M6: =IFERROR(_xlfn.XLOOKUP($C6,'Pesticide Types'!$A$2:$A$519,'Pesticide Types'!$D$2:$D$519),"None") -> HRAC 15
A7: 13 - 2554 | B7: บาติไซด์ 16000 เอสซี (BATICIDE 16000 SC) | C7: bacillus thuringiensis berliner subsp. aizawai | D7: 1.15 x 1010 cfu/ml (16,000 IU/mg SC) | E7: SC | F7: King Biotec Corp Co., Ltd. PRC | G7: ไอ ซี พี ลัดดา บจก. | H7: ไอ ซี พี ลัดดา บจก. | I7: ไอ ซี พี ลัดดา บจก. | J7: 27/05/2023 | K7: 26/05/2029 | L7: =IFERROR(_xlfn.XLOOKUP($C7,'Pesticide Types'!$A$2:$A$519,'Pesticide Types'!$B$2:$B$519),"Unclassified") -> Insecticide | M7: =IFERROR(_xlfn.XLOOKUP($C7,'Pesticide Types'!$A$2:$A$519,'Pesticide Types'!$D$2:$D$519),"None") -> IRAC 11A
A8: 19 - 2554 | B8: อมิสตา (Amistar) | C8: azoxystrobin | D8: 25%W/V | E8: SC | F8: Syngenta Limited, UK; Syngenta Production France S.A.S., France | G8: ซินเจนทา ครอป โปรเทคชั่น บจก. | H8: ซินเจนทา ครอป โปรเทคชั่น บจก. | I8: ซินเจนทา ครอป โปรเทคชั่น บจก. | J8: 05/07/2023 | K8: 04/07/2029 | L8: =IFERROR(_xlfn.XLOOKUP($C8,'Pesticide Types'!$A$2:$A$519,'Pesticide Types'!$B$2:$B$519),"Unclassified") -> Fungicide | M8: =IFERROR(_xlfn.XLOOKUP($C8,'Pesticide Types'!$A$2:$A$519,'Pesticide Types'!$D$2:$D$519),"None") -> FRAC 11
A9: 20 - 2554 | B9: อมิสตา | C9: azoxystrobin | D9: 25%W/V | E9: SC | F9: Syngenta Limited, UK; Syngenta Production France S.A.S., France | G9: ซินเจนทา ครอป โปรเทคชั่น บจก. | H9: ซินเจนทา ครอป โปรเทคชั่น บจก. | I9: ซินเจนทา ครอป โปรเทคชั่น บจก. | J9: 05/07/2023 | K9: 04/07/2029 | L9: =IFERROR(_xlfn.XLOOKUP($C9,'Pesticide Types'!$A$2:$A$519,'Pesticide Types'!$B$2:$B$519),"Unclassified") -> Fungicide | M9: =IFERROR(_xlfn.XLOOKUP($C9,'Pesticide Types'!$A$2:$A$519,'Pesticide Types'!$D$2:$D$519),"None") -> FRAC 11
A10: 23 - 2554 | B10: ไพน์ ฟอส (Pine Fos) | C10: phosphonic acid | D10: 40%W/V | E10: SL | F10: Liquid Fertiliser Pty. Ltd., Australia | G10: ออสก้าร์ อะโกร บจก. | H10: ออสก้าร์ อะโกร บจก. | I10: ออสก้าร์ อะโกร บจก. | J10: 26/07/2023 | K10: 25/07/2029 | L10: =IFERROR(_xlfn.XLOOKUP($C10,'Pesticide Types'!$A$2:$A$519,'Pesticide Types'!$B$2:$B$519),"Unclassified") -> Fungicide | M10: =IFERROR(_xlfn.XLOOKUP($C10,'Pesticide Types'!$A$2:$A$519,'Pesticide Types'!$D$2:$D$519),"None") -> FRAC P07
A11: 58 - 2554 | B11: อาเทีย (Artea) | C11: cyproconazole+propiconazole | D11: 8%+25%W/V | E11: EC | F11: Syngenta Vietnam Ltd., Vietnam | G11: ซินเจนทา ครอป โปรเทคชั่น บจก. | H11: ซินเจนทา ครอป โปรเทคชั่น บจก. | I11: ซินเจนทา ครอป โปรเทคชั่น บจก. | J11: 30/08/2023 | K11: 29/08/2029 | L11: =IFERROR(_xlfn.XLOOKUP($C11,'Pesticide Types'!$A$2:$A$519,'Pesticide Types'!$B$2:$B$519),"Unclassified") -> Unclassified | M11: =IFERROR(_xlfn.XLOOKUP($C11,'Pesticide Types'!$A$2:$A$519,'Pesticide Types'!$D$2:$D$519),"None") -> None
A12: 68 - 2554 | B12: คาโอ-จิน (CAO-JIN) | C12: pendimethalin | D12: 33%W/V | E12: EC | F12: Sinon Corporation Taiwan R.O.C.; Sinon Chemical (China) Co., Ltd. PRC | G12: ซิงหนง (ประเทศไทย) | H12: ซิงหนง (ประเทศไทย) | I12: ซิงหนง (ประเทศไทย) บจก. | J12: 08/09/2023 | K12: 07/09/2029 | L12: =IFERROR(_xlfn.XLOOKUP($C12,'Pesticide Types'!$A$2:$A$519,'Pesticide Types'!$B$2:$B$519),"Unclassified") -> Herbicide | M12: =IFERROR(_xlfn.XLOOKUP($C12,'Pesticide Types'!$A$2:$A$519,'Pesticide Types'!$D$2:$D$519),"None") -> HRAC 3
A13: 71 - 2554 | B13: อีโคแมกซ์ (ECOMAX) | C13: glyphosate-isopropylammonium | D13: 48%W/V | E13: SL | F13: CP Manufacturing Sdn Bhd., Malaysia | G13: คอร์ป โพรเทคชั่น อะโกร (ประเทศไทย) | H13: คอร์ปโพรเทคชั่น อะโกร (ปท) บจก | I13: คอร์ป โพรเทคชั่น อะโกร (ประเทศไทย) บจก. | J13: 08/09/2023 | K13: 07/09/2029 | L13: =IFERROR(_xlfn.XLOOKUP($C13,'Pesticide Types'!$A$2:$A$519,'Pesticide Types'!$B$2:$B$519),"Unclassified") -> Herbicide | M13: =IFERROR(_xlfn.XLOOKUP($C13,'Pesticide Types'!$A$2:$A$519,'Pesticide Types'!$D$2:$D$519),"None") -> HRAC 9
A14: 82 - 2554 | B14: นาติโว 75 ดับบลิวจี (Nativo 75 WG) | C14: trifloxystrobin+tebuconazole | D14: 25%+50% | E14: WG | F14: Bayer Vietnam Limited, Vietnam | G14: ไบเออร์ไทย บจก. | H14: ไบเออร์ไทย บจก. | I14: ไบเออร์ไทย บจก. | J14: 12/09/2023 | K14: 11/09/2029 | L14: =IFERROR(_xlfn.XLOOKUP($C14,'Pesticide Types'!$A$2:$A$519,'Pesticide Types'!$B$2:$B$519),"Unclassified") -> Unclassified | M14: =IFERROR(_xlfn.XLOOKUP($C14,'Pesticide Types'!$A$2:$A$519,'Pesticide Types'!$D$2:$D$519),"None") -> None
A15: 105 - 2554 | B15: เพลนั่ม 50 ดับบลิวจี (Plenum 50 WG) | C15: pymetrozine | D15: 0.5 | E15: WG | F15: Syngenta Korea Limited, Korea | G15: ซินเจนทา ครอป โปรเทคชั่น บจก. | H15: ซินเจนทา ครอป โปรเทคชั่น บจก. | I15: ซินเจนทา ครอป โปรเทคชั่น บจก. | J15: 30/09/2023 | K15: 29/09/2029 | L15: =IFERROR(_xlfn.XLOOKUP($C15,'Pesticide Types'!$A$2:$A$519,'Pesticide Types'!$B$2:$B$519),"Unclassified") -> Insecticide | M15: =IFERROR(_xlfn.XLOOKUP($C15,'Pesticide Types'!$A$2:$A$519,'Pesticide Types'!$D$2:$D$519),"None") -> IRAC 9B
A16: 110 - 2554 | B16: อิมิดาโคลพริด 70% ดับบลิวจี (Imidacloprid 70 % WG) | C16: imidacloprid | D16: 0.7 | E16: WG | F16: Jiangsu Kesheng Group Co., Ltd. PRC | G16: เอส แอนด์ พี ฟอร์มูเลเตอร์ บจก. | H16: เอส แอนด์ พี ฟอร์มูเลเตอร์ บจก. | I16: เอส แอนด์ พี ฟอร์มูเลเตอร์ บจก. | J16: 04/10/2023 | K16: 03/10/2029 | L16: =IFERROR(_xlfn.XLOOKUP($C16,'Pesticide Types'!$A$2:$A$519,'Pesticide Types'!$B$2:$B$519),"Unclassified") -> Insecticide | M16: =IFERROR(_xlfn.XLOOKUP($C16,'Pesticide Types'!$A$2:$A$519,'Pesticide Types'!$D$2:$D$519),"None") -> IRAC 4A
A17: 111 - 2554 | B17: แพนเทอร่า 40 อีซี | C17: quizalofop-p-tefuryl | D17: 4%W/V | E17: EC | F17: Chemark KFT, Hungary; Arysta LifeScience Ourgree Production sprl, Belgium; Arysta LifeSceience India Limited, India | G17: โซตัส อินเตอร์เนชั่นแนล บจก. | H17: โซตัส อินเตอร์เนชั่นแนล บจก. | I17: โซตัส อินเตอร์เนชั่นแนล บจก. | J17: 10/10/2023 | K17: 09/10/2029 | L17: =IFERROR(_xlfn.XLOOKUP($C17,'Pesticide Types'!$A$2:$A$519,'Pesticide Types'!$B$2:$B$519),"Unclassified") -> Herbicide | M17: =IFERROR(_xlfn.XLOOKUP($C17,'Pesticide Types'!$A$2:$A$519,'Pesticide Types'!$D$2:$D$519),"None") -> HRAC 1
A18: 114 - 2554 | B18: แพนเทอร่า 40 อีซี (Pantera 40 EC) | C18: quizalofop-p-tefuryl | D18: 4%W/V | E18: EC | F18: Arysta LufeScience Ougree Production sprl, Belgium; Arysta LufeScience India Limited, India | G18: โซตัส อินเตอร์เนชั่นแนล บจก. | H18: โซตัส อินเตอร์เนชั่นแนล บจก. | I18: โซตัส อินเตอร์เนชั่นแนล บจก. | J18: 10/10/2023 | K18: 09/10/2029 | L18: =IFERROR(_xlfn.XLOOKUP($C18,'Pesticide Types'!$A$2:$A$519,'Pesticide Types'!$B$2:$B$519),"Unclassified") -> Herbicide | M18: =IFERROR(_xlfn.XLOOKUP($C18,'Pesticide Types'!$A$2:$A$519,'Pesticide Types'!$D$2:$D$519),"None") -> HRAC 1
A19: 137 - 2554 | B19: ไดฟีโนโคนาโซล เทค (Difenoconazole Tech) | C19: difenoconazole | D19: 94%min. | E19: Tech. | F19: Syngenta Crop Protection Monthey SA., Switzerland; Deccan Fine Chemicals (india) Private Limited, India; Youjia Crop Protection Co.,Ltd.PRC | G19: ซินเจนทา ครอป โปรเทคชั่น บจก. | H19: ซินเจนทา ครอป โปรเทคชั่น บจก. | I19: ซินเจนทา ครอป โปรเทคชั่น บจก. | J19: 18/10/2023 | K19: 17/10/2029 | L19: =IFERROR(_xlfn.XLOOKUP($C19,'Pesticide Types'!$A$2:$A$519,'Pesticide Types'!$B$2:$B$519),"Unclassified") -> Fungicide | M19: =IFERROR(_xlfn.XLOOKUP($C19,'Pesticide Types'!$A$2:$A$519,'Pesticide Types'!$D$2:$D$519),"None") -> FRAC 3
A20: 138 - 2554 | B20: โพรพิโคลนาโซล เทค (Propiconazole Tech) | C20: propiconazole | D20: 94%min. | E20: Tech. | F20: Syngenta Crop Protection Monthey AG., Switzerland; NACL Industries Limited, India; Youjia Crop Protection Co., Ltd. PRC | G20: ซินเจนทา ครอป โปรเทคชั่น บจก. | H20: ซินเจนทา ครอป โปรเทคชั่น บจก. | I20: ซินเจนทา ครอป โปรเทคชั่น บจก. | J20: 18/10/2023 | K20: 17/10/2029 | L20: =IFERROR(_xlfn.XLOOKUP($C20,'Pesticide Types'!$A$2:$A$519,'Pesticide Types'!$B$2:$B$519),"Unclassified") -> Fungicide | M20: =IFERROR(_xlfn.XLOOKUP($C20,'Pesticide Types'!$A$2:$A$519,'Pesticide Types'!$D$2:$D$519),"None") -> FRAC 3
A21: 140 - 2554 | B21: ฟังกูราน-โอเอช (Funguran-OH) | C21: copper hydroxide | D21: 0.77 | E21: WP | F21: Cosaco GmbH, Germany | G21: โซตัส อินเตอร์เนชั่นแนล บจก. | H21: โซตัส อินเตอร์เนชั่นแนล บจก. | I21: โซตัส อินเตอร์เนชั่นแนล บจก. | J21: 18/10/2023 | K21: 17/10/2029 | L21: =IFERROR(_xlfn.XLOOKUP($C21,'Pesticide Types'!$A$2:$A$519,'Pesticide Types'!$B$2:$B$519),"Unclassified") -> Fungicide | M21: =IFERROR(_xlfn.XLOOKUP($C21,'Pesticide Types'!$A$2:$A$519,'Pesticide Types'!$D$2:$D$519),"None") -> FRAC M01
A22: 143 - 2554 | B22: อะทราซีน 80% ดับเบิลยูพี (Atrazine 80 % WP) | C22: atrazine | D22: 0.8 | E22: WP | F22: Zhejiang Zhongshan Chemical Industry Group Co., Ltd. PRC | G22: ไอ ซี พี ลัดดา บจก. | H22: ไอ ซี พี ลัดดา บจก. | I22: ไอ ซี พี ลัดดา บจก. | J22: 18/10/2023 | K22: 17/10/2029 | L22: =IFERROR(_xlfn.XLOOKUP($C22,'Pesticide Types'!$A$2:$A$519,'Pesticide Types'!$B$2:$B$519),"Unclassified") -> Herbicide | M22: =IFERROR(_xlfn.XLOOKUP($C22,'Pesticide Types'!$A$2:$A$519,'Pesticide Types'!$D$2:$D$519),"None") -> HRAC 5
A23: 146 - 2554 | B23: เฟลกซ์ (Flex) | C23: fomesafen | D23: 25%W/V | E23: SL | F23: Jiangsu Changqing Biotechnology Co., Ltd. PRC | G23: ซินเจนทา ครอป โปรเทคชั่น บจก. | H23: ซินเจนทา ครอป โปรเทคชั่น บจก. | I23: ซินเจนทา ครอป โปรเทคชั่น บจก. | J23: 19/10/2023 | K23: 18/10/2029 | L23: =IFERROR(_xlfn.XLOOKUP($C23,'Pesticide Types'!$A$2:$A$519,'Pesticide Types'!$B$2:$B$519),"Unclassified") -> Herbicide | M23: =IFERROR(_xlfn.XLOOKUP($C23,'Pesticide Types'!$A$2:$A$519,'Pesticide Types'!$D$2:$D$519),"None") -> HRAC 14
A24: 147 - 2554 | B24: เฟลกซ์ | C24: fomesafen | D24: 25%W/V | E24: SL | F24: Jiangsu Changqing Biotechnology Co., Ltd. PRC | G24: ซินเจนทา ครอป โปรเทคชั่น บจก. | H24: ซินเจนทา ครอป โปรเทคชั่น บจก. | I24: ซินเจนทา ครอป โปรเทคชั่น บจก. | J24: 19/10/2023 | K24: 18/10/2029 | L24: =IFERROR(_xlfn.XLOOKUP($C24,'Pesticide Types'!$A$2:$A$519,'Pesticide Types'!$B$2:$B$519),"Unclassified") -> Herbicide | M24: =IFERROR(_xlfn.XLOOKUP($C24,'Pesticide Types'!$A$2:$A$519,'Pesticide Types'!$D$2:$D$519),"None") -> HRAC 14
A25: 148 - 2554 | B25: อามูเร่ (Armure) | C25: difenoconazole+propiconazole | D25: 15%+15%W/V | E25: EC | F25: PT Syngenta Indonesia, Indonesia | G25: ซินเจนทา ครอป โปรเทคชั่น บจก. | H25: ซินเจนทา ครอป โปรเทคชั่น บจก. | I25: ซินเจนทา ครอป โปรเทคชั่น บจก. | J25: 19/10/2023 | K25: 18/10/2029 | L25: =IFERROR(_xlfn.XLOOKUP($C25,'Pesticide Types'!$A$2:$A$519,'Pesticide Types'!$B$2:$B$519),"Unclassified") -> Unclassified | M25: =IFERROR(_xlfn.XLOOKUP($C25,'Pesticide Types'!$A$2:$A$519,'Pesticide Types'!$D$2:$D$519),"None") -> None
A26: 149 - 2554 | B26: บูโพรเฟซิน 40 เอสซี (Buprofezin 40 SC) | C26: buprofezin | D26: 40%W/V | E26: SC | F26: Jiangsu Changlong Agrochemicals Co., Ltd. PRC | G26: เมอริสเต็ม | H26: เมอริสเต็ม | I26: เวล อกริเทค บจก. | J26: 19/10/2023 | K26: 18/10/2029 | L26: =IFERROR(_xlfn.XLOOKUP($C26,'Pesticide Types'!$A$2:$A$519,'Pesticide Types'!$B$2:$B$519),"Unclassified") -> Insecticide | M26: =IFERROR(_xlfn.XLOOKUP($C26,'Pesticide Types'!$A$2:$A$519,'Pesticide Types'!$D$2:$D$519),"None") -> IRAC 16
A27: 150 - 2554 | B27: บูโพรเฟซิน 25 ดับลิวพี (Buprofezin 25 WP) | C27: buprofezin | D27: 0.25 | E27: WP | F27: Jiangsu Changlong Agrochemicals Co., Ltd. PRC | G27: เมอริสเต็ม | H27: เมอริสเต็ม | I27: เมอริสเต็ม บจก. | J27: 19/10/2023 | K27: 18/10/2029 | L27: =IFERROR(_xlfn.XLOOKUP($C27,'Pesticide Types'!$A$2:$A$519,'Pesticide Types'!$B$2:$B$519),"Unclassified") -> Insecticide | M27: =IFERROR(_xlfn.XLOOKUP($C27,'Pesticide Types'!$A$2:$A$519,'Pesticide Types'!$D$2:$D$519),"None") -> IRAC 16
A28: 151 - 2554 | B28: ดูอัล โกลด์ | C28: s-metolachlor | D28: 96%W/V | E28: EC | F28: Chemark ZRT., Hungary; Syngenta Production France S.A.S., France; Syngenta (Suzhou) Crop Protection Co., Ltd. PRC | G28: ซินเจนทา ครอป โปรเทคชั่น บจก. | H28: ซินเจนทา ครอป โปรเทคชั่น บจก. | I28: ซินเจนทา ครอป โปรเทคชั่น บจก. | J28: 19/10/2023 | K28: 18/10/2029 | L28: =IFERROR(_xlfn.XLOOKUP($C28,'Pesticide Types'!$A$2:$A$519,'Pesticide Types'!$B$2:$B$519),"Unclassified") -> Herbicide | M28: =IFERROR(_xlfn.XLOOKUP($C28,'Pesticide Types'!$A$2:$A$519,'Pesticide Types'!$D$2:$D$519),"None") -> HRAC 15
A29: 152 - 2554 | B29: อามูเร่ | C29: difenoconazole+propiconazole | D29: 15%+15%W/V | E29: EC | F29: PT Syngenta Indonesia, Indonesia | G29: ซินเจนทา ครอป โปรเทคชั่น บจก. | H29: ซินเจนทา ครอป โปรเทคชั่น บจก. | I29: ซินเจนทา ครอป โปรเทคชั่น บจก. | J29: 19/10/2023 | K29: 18/10/2029 | L29: =IFERROR(_xlfn.XLOOKUP($C29,'Pesticide Types'!$A$2:$A$519,'Pesticide Types'!$B$2:$B$519),"Unclassified") -> Unclassified | M29: =IFERROR(_xlfn.XLOOKUP($C29,'Pesticide Types'!$A$2:$A$519,'Pesticide Types'!$D$2:$D$519),"None") -> None
A30: 157 - 2554 | B30: สกอร์ (Score) | C30: difenoconazole | D30: 25%W/V | E30: EC | F30: PT Syngenta Indonesia, Indonesia | G30: ซินเจนทา ครอป โปรเทคชั่น บจก. | H30: ซินเจนทา ครอป โปรเทคชั่น บจก. | I30: ซินเจนทา ครอป โปรเทคชั่น บจก. | J30: 19/10/2023 | K30: 18/10/2029 | L30: =IFERROR(_xlfn.XLOOKUP($C30,'Pesticide Types'!$A$2:$A$519,'Pesticide Types'!$B$2:$B$519),"Unclassified") -> Fungicide | M30: =IFERROR(_xlfn.XLOOKUP($C30,'Pesticide Types'!$A$2:$A$519,'Pesticide Types'!$D$2:$D$519),"None") -> FRAC 3
A31: 158 - 2554 | B31: ราวด์อั้พ (Roundup) | C31: glyphosate-isopropylammonium | D31: 48%W/V | E31: SL | F31: Monsanto Malaysia Sdn., Bhd. Malaysia | G31: มอนซานโต้ ไทยแลนด์ | H31: มอนซานโต้ ไทยแลนด์ | I31: มอนซานโต้ ไทยแลนด์ บจก. | J31: 19/10/2023 | K31: 18/10/2029 | L31: =IFERROR(_xlfn.XLOOKUP($C31,'Pesticide Types'!$A$2:$A$519,'Pesticide Types'!$B$2:$B$519),"Unclassified") -> Herbicide | M31: =IFERROR(_xlfn.XLOOKUP($C31,'Pesticide Types'!$A$2:$A$519,'Pesticide Types'!$D$2:$D$519),"None") -> HRAC 9
A32: 171 - 2554 | B32: โซลิโต้ (Solito) | C32: pretilachlor+pyribenzoxim | D32: 30%+2%W/V | E32: EC | F32: Asiatic Agricultural Industries Pte., Ltd., Singapore; Syngenta Vietnam Ltd., Vietnam | G32: ซินเจนทา ครอป โปรเทคชั่น บจก. | H32: ซินเจนทา ครอป โปรเทคชั่น บจก. | I32: ซินเจนทา ครอป โปรเทคชั่น บจก. | J32: 25/10/2023 | K32: 24/10/2029 | L32: =IFERROR(_xlfn.XLOOKUP($C32,'Pesticide Types'!$A$2:$A$519,'Pesticide Types'!$B$2:$B$519),"Unclassified") -> Unclassified | M32: =IFERROR(_xlfn.XLOOKUP($C32,'Pesticide Types'!$A$2:$A$519,'Pesticide Types'!$D$2:$D$519),"None") -> None
A33: 172 - 2554 | B33: แอคทารา 25 ดับบลิวจี (Actara 25 WG) | C33: thiamethoxam | D33: 0.25 | E33: WG | F33: Syngenta India Private Limited, India; Deccan Fine Chemicals (India) Private Limited, India; Syngenta Korea Limited, Republic of Korea | G33: ซินเจนทา ครอป โปรเทคชั่น บจก. | H33: ซินเจนทา ครอป โปรเทคชั่น บจก. | I33: ซินเจนทา ครอป โปรเทคชั่น บจก. | J33: 25/10/2023 | K33: 24/10/2029 | L33: =IFERROR(_xlfn.XLOOKUP($C33,'Pesticide Types'!$A$2:$A$519,'Pesticide Types'!$B$2:$B$519),"Unclassified") -> Insecticide | M33: =IFERROR(_xlfn.XLOOKUP($C33,'Pesticide Types'!$A$2:$A$519,'Pesticide Types'!$D$2:$D$519),"None") -> IRAC 4A
A34: 173 - 2554 | B34: เวอตาโก 40 ดับบลิวจี (Virtako 40 WG) | C34: chlorantraniliprole+thiamethoxam | D34: 20%+20% | E34: WG | F34: Gowan Milling, USA; Syngenta Nantong Crop Protection Co., Ltd. PRC | G34: ซินเจนทา ครอป โปรเทคชั่น บจก. | H34: ซินเจนทา ครอป โปรเทคชั่น บจก. | I34: ซินเจนทา ครอป โปรเทคชั่น บจก. | J34: 25/10/2023 | K34: 24/10/2029 | L34: =IFERROR(_xlfn.XLOOKUP($C34,'Pesticide Types'!$A$2:$A$519,'Pesticide Types'!$B$2:$B$519),"Unclassified") -> Unclassified | M34: =IFERROR(_xlfn.XLOOKUP($C34,'Pesticide Types'!$A$2:$A$519,'Pesticide Types'!$D$2:$D$519),"None") -> None
A35: 178 - 2554 | B35: อะมีทรีน 80% ดับบลิวพี (Ametryn 80% WP) | C35: ametryn | D35: 0.8 | E35: WP | F35: Zhejiang Zhongshan Chemical Industry Group Co., Ltd. PRC | G35: เอราวัณ เคมีเกษตร บจก. | H35: เอราวัณ เคมีเกษตร บจก. | I35: เอราวัณ เคมีเกษตร บจก. | J35: 11/11/2023 | K35: 10/11/2029 | L35: =IFERROR(_xlfn.XLOOKUP($C35,'Pesticide Types'!$A$2:$A$519,'Pesticide Types'!$B$2:$B$519),"Unclassified") -> Herbicide | M35: =IFERROR(_xlfn.XLOOKUP($C35,'Pesticide Types'!$A$2:$A$519,'Pesticide Types'!$D$2:$D$519),"None") -> HRAC 5
A36: 180 - 2554 | B36: โคลมาโซน 48% อีซี (Clomazone 48 % EC) | C36: clomazone | D36: 48%W/V | E36: EC | F36: Jiangsu Jiannong ABA Agrochemical Co., Ltd., PRC | G36: โกลบอล ครอปส์ บจก. | H36: โกลบอล ครอปส์ บจก. | I36: โกลบอล ครอปส์ บจก. | J36: 14/11/2023 | K36: 13/11/2029 | L36: =IFERROR(_xlfn.XLOOKUP($C36,'Pesticide Types'!$A$2:$A$519,'Pesticide Types'!$B$2:$B$519),"Unclassified") -> Herbicide | M36: =IFERROR(_xlfn.XLOOKUP($C36,'Pesticide Types'!$A$2:$A$519,'Pesticide Types'!$D$2:$D$519),"None") -> HRAC 13
A37: 181 - 2554 | B37: โกลเซ็น (Glozen) | C37: butachlor | D37: 60%W/V | E37: EW | F37: Shandong Binnong Technology Co., Ltd. PRC | G37: โกลบอล ครอปส์ บจก. | H37: โกลบอล ครอปส์ บจก. | I37: โกลบอล ครอปส์ บจก. | J37: 14/11/2023 | K37: 13/11/2029 | L37: =IFERROR(_xlfn.XLOOKUP($C37,'Pesticide Types'!$A$2:$A$519,'Pesticide Types'!$B$2:$B$519),"Unclassified") -> Herbicide | M37: =IFERROR(_xlfn.XLOOKUP($C37,'Pesticide Types'!$A$2:$A$519,'Pesticide Types'!$D$2:$D$519),"None") -> HRAC 15
A38: 184 - 2554 | B38: สปาย (Spy) | C38: bispyribac-sodium | D38: 0.2 | E38: WP | F38: Jiangsu Institute of Ecomones Co., Ltd. PRC | G38: ซัน อโกรเทค | H38: ซัน อโกรเทค | I38: ซัน อโกรเทค บจก. | J38: 15/11/2023 | K38: 14/11/2029 | L38: =IFERROR(_xlfn.XLOOKUP($C38,'Pesticide Types'!$A$2:$A$519,'Pesticide Types'!$B$2:$B$519),"Unclassified") -> Herbicide | M38: =IFERROR(_xlfn.XLOOKUP($C38,'Pesticide Types'!$A$2:$A$519,'Pesticide Types'!$D$2:$D$519),"None") -> HRAC 2
A39: 187 - 2554 | B39: บาซิน่า (Bacina) | C39: bacillus thuringiensis subsp. aizawai | D39: 3.70 x 109 cfu/g [32,000 IU/mg (4%WP)] | E39: WP | F39: King Biotec Corp Co., Ltd. PRC | G39: ไอ ซี พี ลัดดา บจก. | H39: ไอ ซี พี ลัดดา บจก. | I39: ไอ ซี พี ลัดดา บจก. | J39: 15/11/2023 | K39: 14/11/2029 | L39: =IFERROR(_xlfn.XLOOKUP($C39,'Pesticide Types'!$A$2:$A$519,'Pesticide Types'!$B$2:$B$519),"Unclassified") -> Insecticide | M39: =IFERROR(_xlfn.XLOOKUP($C39,'Pesticide Types'!$A$2:$A$519,'Pesticide Types'!$D$2:$D$519),"None") -> IRAC 11A
A40: 188 - 2554 | B40: โคลมาโซน 48 อีซี (Clomazone 480 EC) | C40: clomazone | D40: 48%W/V | E40: EC | F40: Jiangsu Heben Biochemical Co., Ltd. PRC | G40: ไอ ซี พี ลัดดา บจก. | H40: ไอ ซี พี ลัดดา บจก. | I40: ไอ ซี พี ลัดดา บจก. | J40: 15/11/2023 | K40: 14/11/2029 | L40: =IFERROR(_xlfn.XLOOKUP($C40,'Pesticide Types'!$A$2:$A$519,'Pesticide Types'!$B$2:$B$519),"Unclassified") -> Herbicide | M40: =IFERROR(_xlfn.XLOOKUP($C40,'Pesticide Types'!$A$2:$A$519,'Pesticide Types'!$D$2:$D$519),"None") -> HRAC 13
A41: 192 - 2554 | B41: มาจีสเตอร์ 48 อีซี (Magister 480EC) | C41: clomazone | D41: 48%W/V | E41: EC | F41: PT Bina Guna Kimia , Indonesia | G41: เอฟเอ็ม ซี เอจี (ประเทศไทย) | H41: เอฟเอ็ม ซี | I41: เอฟเอ็ม ซี เคมิคัล (ประเทศไทย) บจก. | J41: 25/11/2023 | K41: 24/11/2029 | L41: =IFERROR(_xlfn.XLOOKUP($C41,'Pesticide Types'!$A$2:$A$519,'Pesticide Types'!$B$2:$B$519),"Unclassified") -> Herbicide | M41: =IFERROR(_xlfn.XLOOKUP($C41,'Pesticide Types'!$A$2:$A$519,'Pesticide Types'!$D$2:$D$519),"None") -> HRAC 13
A42: 195 - 2554 | B42: โกล (Goal) | C42: oxyfluorfen | D42: 23.5%W/V | E42: EC | F42: Hangzhou Nutrichem Company Limited. PRC | G42: ดาว อะโกรไซแอนส์ (ประเทศไทย) บจก. | H42: ดาว อะโกรไซแอนส์ (ประเทศไทย) บจก. | I42: คอร์เทวา อะกริไซเอนซ์ (ประเทศไทย) บจก. | J42: 30/11/2023 | K42: 29/11/2030 | L42: =IFERROR(_xlfn.XLOOKUP($C42,'Pesticide Types'!$A$2:$A$519,'Pesticide Types'!$B$2:$B$519),"Unclassified") -> Herbicide | M42: =IFERROR(_xlfn.XLOOKUP($C42,'Pesticide Types'!$A$2:$A$519,'Pesticide Types'!$D$2:$D$519),"None") -> HRAC 14
A43: 197 - 2554 | B43: - | C43: bacillus thuringiensis subsp. kurstaki | D43: 6.58 x 109 cfu/ml (10,600 IU/mg) | E43: SC | F43: Valent BioSciences LLC., U.S.A | G43: เทพวัฒนา บจก. | H43: เทพวัฒนา บจก. | I43: เทพวัฒนา บจก. | J43: 30/11/2023 | K43: 29/11/2029 | L43: =IFERROR(_xlfn.XLOOKUP($C43,'Pesticide Types'!$A$2:$A$519,'Pesticide Types'!$B$2:$B$519),"Unclassified") -> Insecticide | M43: =IFERROR(_xlfn.XLOOKUP($C43,'Pesticide Types'!$A$2:$A$519,'Pesticide Types'!$D$2:$D$519),"None") -> IRAC 11A
A44: 199 - 2554 | B44: เซนทารี (XenTari) | C44: bacillus thuringiensis subsp. aizawai | D44: 1.60 x 1011 cfu/g (35,000 DBMU/mg) | E44: WG | F44: Valent BioSciences LLC., U.S.A | G44: โซตัส อินเตอร์เนชั่นแนล บจก. | H44: โซตัส อินเตอร์เนชั่นแนล บจก. | I44: โซตัส อินเตอร์เนชั่นแนล บจก. | J44: 30/11/2023 | K44: 29/11/2029 | L44: =IFERROR(_xlfn.XLOOKUP($C44,'Pesticide Types'!$A$2:$A$519,'Pesticide Types'!$B$2:$B$519),"Unclassified") -> Insecticide | M44: =IFERROR(_xlfn.XLOOKUP($C44,'Pesticide Types'!$A$2:$A$519,'Pesticide Types'!$D$2:$D$519),"None") -> IRAC 11A
A45: 200 - 2554 | B45: รีวัส เอ็ม เซต 65 ดับบลิวจี (Revus MZ 65 WG) | C45: mancozeb+mandipropamid | D45: 60%+5% | E45: WG | F45: IPT Pergande GmbH, Germany | G45: ซินเจนทา ครอป โปรเทคชั่น บจก. | H45: ซินเจนทา ครอป โปรเทคชั่น บจก. | I45: ซินเจนทา ครอป โปรเทคชั่น บจก. | J45: 30/11/2023 | K45: 29/11/2029 | L45: =IFERROR(_xlfn.XLOOKUP($C45,'Pesticide Types'!$A$2:$A$519,'Pesticide Types'!$B$2:$B$519),"Unclassified") -> Unclassified | M45: =IFERROR(_xlfn.XLOOKUP($C45,'Pesticide Types'!$A$2:$A$519,'Pesticide Types'!$D$2:$D$519),"None") -> None
A46: 201 - 2554 | B46: ฟลิ้นท์ (Flint) | C46: trifloxystrobin | D46: 0.5 | E46: WG | F46: Bayer AG, Germany | G46: ไบเออร์ไทย บจก. | H46: ไบเออร์ไทย บจก. | I46: ไบเออร์ไทย บจก. | J46: 30/11/2023 | K46: 29/11/2029 | L46: =IFERROR(_xlfn.XLOOKUP($C46,'Pesticide Types'!$A$2:$A$519,'Pesticide Types'!$B$2:$B$519),"Unclassified") -> Fungicide | M46: =IFERROR(_xlfn.XLOOKUP($C46,'Pesticide Types'!$A$2:$A$519,'Pesticide Types'!$D$2:$D$519),"None") -> FRAC 11
A47: 202 - 2554 | B47: วิป (Whip) | C47: fenoxaprop-p-ethyl | D47: 6.9%W/V | E47: EW | F47: Bayer Vietnam Limited, Vietnam | G47: ไบเออร์ไทย บจก. | H47: ไบเออร์ไทย บจก. | I47: ไบเออร์ไทย บจก. | J47: 30/11/2023 | K47: 29/11/2029 | L47: =IFERROR(_xlfn.XLOOKUP($C47,'Pesticide Types'!$A$2:$A$519,'Pesticide Types'!$B$2:$B$519),"Unclassified") -> Herbicide | M47: =IFERROR(_xlfn.XLOOKUP($C47,'Pesticide Types'!$A$2:$A$519,'Pesticide Types'!$D$2:$D$519),"None") -> HRAC 1
A48: 204 - 2554 | B48: การ์ลอน (Garlon) | C48: triclopyr butoxyethyl ester | D48: 66.8%W/V | E48: EC | F48: PT. Corteva Agriscience Manufacturing Indonesia, Indonesia | G48: ดาว อะโกรไซแอนส์ (ประเทศไทย) บจก. | H48: ดาว อะโกรไซแอนส์ (ประเทศไทย) บจก. | I48: คอร์เทวา อะกริไซเอนซ์ (ประเทศไทย) บจก. | J48: 30/11/2023 | K48: 29/11/2029 | L48: =IFERROR(_xlfn.XLOOKUP($C48,'Pesticide Types'!$A$2:$A$519,'Pesticide Types'!$B$2:$B$519),"Unclassified") -> Herbicide | M48: =IFERROR(_xlfn.XLOOKUP($C48,'Pesticide Types'!$A$2:$A$519,'Pesticide Types'!$D$2:$D$519),"None") -> HRAC 4
A49: 208 - 2554 | B49: แอนวิล (Anvil) | C49: hexaconazole | D49: 5%W/V | E49: SC | F49: Asiatic Agricultural Industries Pte., Ltd., Singapore; Mastra Industries Sdn Bhd, Malaysia; Syngenta Vietnam Ltd., Vietnam; Nufarm Malaysia Sdn. Bhd., Malaysia | G49: ซินเจนทา ครอป โปรเทคชั่น บจก. | H49: ซินเจนทา ครอป โปรเทคชั่น บจก. | I49: ซินเจนทา ครอป โปรเทคชั่น บจก. | J49: 30/11/2023 | K49: 29/11/2029 | L49: =IFERROR(_xlfn.XLOOKUP($C49,'Pesticide Types'!$A$2:$A$519,'Pesticide Types'!$B$2:$B$519),"Unclassified") -> Fungicide | M49: =IFERROR(_xlfn.XLOOKUP($C49,'Pesticide Types'!$A$2:$A$519,'Pesticide Types'!$D$2:$D$519),"None") -> FRAC 3
A50: 210 - 2554 | B50: ทิลท์ (Tilt) | C50: propiconazole | D50: 25%W/V | E50: EC | F50: Syngenta South Africa (Pty) Limited, South Africa; Syngenta Korea Limited, Republic of Korea | G50: ซินเจนทา ครอป โปรเทคชั่น บจก. | H50: ซินเจนทา ครอป โปรเทคชั่น บจก. | I50: ซินเจนทา ครอป โปรเทคชั่น บจก. | J50: 30/11/2023 | K50: 29/11/2029 | L50: =IFERROR(_xlfn.XLOOKUP($C50,'Pesticide Types'!$A$2:$A$519,'Pesticide Types'!$B$2:$B$519),"Unclassified") -> Fungicide | M50: =IFERROR(_xlfn.XLOOKUP($C50,'Pesticide Types'!$A$2:$A$519,'Pesticide Types'!$D$2:$D$519),"None") -> FRAC 3
A51: 213 - 2554 | B51: อะมีทรีน 80% ดับเบิลยูพี (Ametryn 80 % WP) | C51: ametryn | D51: 0.8 | E51: WP | F51: Zhejiang Zhongshan Chemical Industry Group Co., Ltd. PRC | G51: ไอ ซี พี ลัดดา บจก. | H51: ไอ ซี พี ลัดดา บจก. | I51: ไอ ซี พี ลัดดา บจก. | J51: 30/11/2023 | K51: 29/11/2029 | L51: =IFERROR(_xlfn.XLOOKUP($C51,'Pesticide Types'!$A$2:$A$519,'Pesticide Types'!$B$2:$B$519),"Unclassified") -> Herbicide | M51: =IFERROR(_xlfn.XLOOKUP($C51,'Pesticide Types'!$A$2:$A$519,'Pesticide Types'!$D$2:$D$519),"None") -> HRAC 5
A52: 217 - 2554 | B52: ออติวา (Ortiva) | C52: azoxystrobin+difenoconazole | D52: 20%+12.5%W/V | E52: SC | F52: Syngenta Limited, UK; Syngenta Korea Limited., Republic of Korea | G52: ซินเจนทา ครอป โปรเทคชั่น บจก. | H52: ซินเจนทา ครอป โปรเทคชั่น บจก. | I52: ซินเจนทา ครอป โปรเทคชั่น บจก. | J52: 30/11/2023 | K52: 29/11/2029 | L52: =IFERROR(_xlfn.XLOOKUP($C52,'Pesticide Types'!$A$2:$A$519,'Pesticide Types'!$B$2:$B$519),"Unclassified") -> Unclassified | M52: =IFERROR(_xlfn.XLOOKUP($C52,'Pesticide Types'!$A$2:$A$519,'Pesticide Types'!$D$2:$D$519),"None") -> None
A53: 219 - 2554 | B53: เรนโบว์ 2,4-ดี ไดเมทิลเอมีน ซอลต์ 840 เอสแอล (Rainbow 24-D Dimethylamine Salt 840 SL) | C53: 2,4-d-dimethylammonium | D53: 84%W/V | E53: SL | F53: Shandong Weifang Rainbow Chemical Co., Ltd. PRC | G53: โกลบอล ครอปส์ บจก. | H53: โกลบอล ครอปส์ บจก. | I53: โกลบอล ครอปส์ บจก. | J53: 30/11/2023 | K53: 29/11/2029 | L53: =IFERROR(_xlfn.XLOOKUP($C53,'Pesticide Types'!$A$2:$A$519,'Pesticide Types'!$B$2:$B$519),"Unclassified") -> Herbicide | M53: =IFERROR(_xlfn.XLOOKUP($C53,'Pesticide Types'!$A$2:$A$519,'Pesticide Types'!$D$2:$D$519),"None") -> HRAC 4
A54: 220 - 2554 | B54: โกลแจ็กซ์ (GLOJACK) | C54: abamectin | D54: 1.8%W/V | E54: EC | F54: Zhejiang Shenghua Biok Biology Co., Ltd. PRC | G54: โกลบอล ครอปส์ บจก. | H54: โกลบอล ครอปส์ บจก. | I54: โกลบอล ครอปส์ บจก. | J54: 30/11/2023 | K54: 29/11/2029 | L54: =IFERROR(_xlfn.XLOOKUP($C54,'Pesticide Types'!$A$2:$A$519,'Pesticide Types'!$B$2:$B$519),"Unclassified") -> Insecticide | M54: =IFERROR(_xlfn.XLOOKUP($C54,'Pesticide Types'!$A$2:$A$519,'Pesticide Types'!$D$2:$D$519),"None") -> IRAC 6
A55: 221 - 2554 | B55: เอเทร็ก 90 ดับบลิวจี (Aatrex 90 WG) | C55: atrazine | D55: 0.9 | E55: WG | F55: Syngenta Crop Protection Inc., U.S.A. | G55: ซินเจนทา ครอป โปรเทคชั่น บจก. | H55: ซินเจนทา ครอป โปรเทคชั่น บจก. | I55: ซินเจนทา ครอป โปรเทคชั่น บจก. | J55: 30/11/2023 | K55: 29/11/2029 | L55: =IFERROR(_xlfn.XLOOKUP($C55,'Pesticide Types'!$A$2:$A$519,'Pesticide Types'!$B$2:$B$519),"Unclassified") -> Herbicide | M55: =IFERROR(_xlfn.XLOOKUP($C55,'Pesticide Types'!$A$2:$A$519,'Pesticide Types'!$D$2:$D$519),"None") -> HRAC 5
A56: 222 - 2554 | B56: อามูเร่ | C56: difenoconazole+propiconazole | D56: 15%+15%W/V | E56: EC | F56: ซินเจนทา ครอป โปรเทคชั่น บจก. (นำเข้าสารเข้มข้น difenoconazole 94 % min. Tech จาก Syngenta Crop Protection Monthey SA, Switzerland; Deccan fine Chemicals (India) | G56: ซินเจนทา ครอป โปรเทคชั่น บจก. | H56: ซินเจนทา ครอป โปรเทคชั่น บจก. | I56: ซินเจนทา ครอป โปรเทคชั่น บจก. | J56: 30/11/2023 | K56: 29/11/2029 | L56: =IFERROR(_xlfn.XLOOKUP($C56,'Pesticide Types'!$A$2:$A$519,'Pesticide Types'!$B$2:$B$519),"Unclassified") -> Unclassified | M56: =IFERROR(_xlfn.XLOOKUP($C56,'Pesticide Types'!$A$2:$A$519,'Pesticide Types'!$D$2:$D$519),"None") -> None
A57: 223 - 2554 | B57: ออติวา | C57: azoxystrobin+difenoconazole | D57: 20%+12.5%W/V | E57: SC | F57: PSryinvgaeten tLai mLiimteidte, dIn, dUiKa; ;Y Soyunjigae Cntrao pK oPrreoate ction Limited., Rekpublic of Korea | G57: ซินเจนทา ครอป โปรเทคชั่น บจก. | H57: ซินเจนทา ครอป โปรเทคชั่น บจก. | I57: ซินเจนทา ครอป โปรเทคชั่น บจก. | J57: 30/11/2023 | K57: 29/11/2029 | L57: =IFERROR(_xlfn.XLOOKUP($C57,'Pesticide Types'!$A$2:$A$519,'Pesticide Types'!$B$2:$B$519),"Unclassified") -> Unclassified | M57: =IFERROR(_xlfn.XLOOKUP($C57,'Pesticide Types'!$A$2:$A$519,'Pesticide Types'!$D$2:$D$519),"None") -> None
A58: 226 - 2554 | B58: สกอร์ | C58: difenoconazole | D58: 25%W/V | E58: EC | F58: ซินเจนทา ครอป โปรเทคชั่น บจก. (นำเข้าสารเข้มข้นจาก Syngenta Crop Protection Monthey SA, Switzerland; Deccan Fine Chemicals (India) Private Limited, India; Youjia Crop Protection | G58: ซินเจนทา ครอป โปรเทคชั่น บจก. | H58: ซินเจนทา ครอป โปรเทคชั่น บจก. | I58: ซินเจนทา ครอป โปรเทคชั่น บจก. | J58: 30/11/2023 | K58: 29/11/2029 | L58: =IFERROR(_xlfn.XLOOKUP($C58,'Pesticide Types'!$A$2:$A$519,'Pesticide Types'!$B$2:$B$519),"Unclassified") -> Fungicide | M58: =IFERROR(_xlfn.XLOOKUP($C58,'Pesticide Types'!$A$2:$A$519,'Pesticide Types'!$D$2:$D$519),"None") -> FRAC 3
A59: 228 - 2554 | B59: รอนสตาร์ (Ronstar) | C59: oxadiazon | D59: 25%W/V | E59: EC | F59: Bayer Vietnam Limited, Vietnam | G59: ไบเออร์ไทย บจก. | H59: ไบเออร์ไทย บจก. | I59: ไบเออร์ไทย บจก. | J59: 30/11/2023 | K59: 29/11/2029 | L59: =IFERROR(_xlfn.XLOOKUP($C59,'Pesticide Types'!$A$2:$A$519,'Pesticide Types'!$B$2:$B$519),"Unclassified") -> Herbicide | M59: =IFERROR(_xlfn.XLOOKUP($C59,'Pesticide Types'!$A$2:$A$519,'Pesticide Types'!$D$2:$D$519),"None") -> HRAC 14
A60: 229 - 2554 | B60: อลัทาคอร์ (Altacor) | C60: chlorantraniliprole | D60: 0.35 | E60: WG | F60: FMC Corporation, USA; PT FMC Agricultural Manufacturing, Indonesia; PT Bina Guna Kimia, Indonesia | G60: เอฟเอ็ม ซี เอจี (ประเทศไทย) | H60: ดูปองท์ (ประเทศไทย) บจก. | I60: บีเอเอสเอฟ (ไทย) บจก. | J60: 30/11/2023 | K60: 29/11/2029 | L60: =IFERROR(_xlfn.XLOOKUP($C60,'Pesticide Types'!$A$2:$A$519,'Pesticide Types'!$B$2:$B$519),"Unclassified") -> Insecticide | M60: =IFERROR(_xlfn.XLOOKUP($C60,'Pesticide Types'!$A$2:$A$519,'Pesticide Types'!$D$2:$D$519),"None") -> IRAC 28
A61: 233 - 2554 | B61: โกลซิน 40 | C61: buprofezin | D61: 40%W/V | E61: SC | F61: Jiangsu Changlong Agrochemical Co., Ltd. PRC | G61: โกลบอล ครอปส์ บจก. | H61: เมอริสเต็ม | I61: โกลบอล ครอปส์ บจก. | J61: 30/11/2023 | K61: 29/11/2029 | L61: =IFERROR(_xlfn.XLOOKUP($C61,'Pesticide Types'!$A$2:$A$519,'Pesticide Types'!$B$2:$B$519),"Unclassified") -> Insecticide | M61: =IFERROR(_xlfn.XLOOKUP($C61,'Pesticide Types'!$A$2:$A$519,'Pesticide Types'!$D$2:$D$519),"None") -> IRAC 16
A62: 234 - 2554 | B62: ฟังกูราน-โอเอช | C62: copper hydroxide | D62: 0.77 | E62: WP | F62: Cosaco GmbH, Germany | G62: โซตัส อินเตอร์เนชั่นแนล บจก. | H62: โซตัส อินเตอร์เนชั่นแนล บจก. | I62: โซตัส อินเตอร์เนชั่นแนล บจก. | J62: 30/11/2023 | K62: 29/11/2029 | L62: =IFERROR(_xlfn.XLOOKUP($C62,'Pesticide Types'!$A$2:$A$519,'Pesticide Types'!$B$2:$B$519),"Unclassified") -> Fungicide | M62: =IFERROR(_xlfn.XLOOKUP($C62,'Pesticide Types'!$A$2:$A$519,'Pesticide Types'!$D$2:$D$519),"None") -> FRAC M01
A63: 237 - 2554 | B63: ฟูม อ๊ กซิน (FUME TOXIN) | C63: aluminium phosphide | D63: 56%TB | E63: TB | F63: Jining High Technology Development Zone Yongfeng Chemical Plant, PRC | G63: เอเซียเพสคอนโทรลแอนด์ อินสเปคชั่น | H63: เอเซียเพสคอนโทรลแอนด์ อินสเปคชั่น | I63: เอเชีย เพสคอนโทรล แอนด์ อินสเปคชั่น บจก. | J63: 06/12/2023 | K63: 05/12/2029 | L63: =IFERROR(_xlfn.XLOOKUP($C63,'Pesticide Types'!$A$2:$A$519,'Pesticide Types'!$B$2:$B$519),"Unclassified") -> Fumigant | M63: =IFERROR(_xlfn.XLOOKUP($C63,'Pesticide Types'!$A$2:$A$519,'Pesticide Types'!$D$2:$D$519),"None") -> IRAC 24A
A64: 238 - 2554 | B64: อะบาเมกติน (Abamectin) | C64: abamectin | D64: 1.8%W/V | E64: EC | F64: Hebei Veyong Bio-Chemical Co., Ltd. PRC | G64: แอ็กโฟรีแพ็กซ์ อินดัสตรีส์ บจก. | H64: แอ็กโฟรีแพ็กซ์ อินดัสตรีส์ บจก. | I64: แอ็กโฟรีแพ็กซ์ อินดัสตรีส์ บจก. | J64: 06/12/2023 | K64: 05/12/2029 | L64: =IFERROR(_xlfn.XLOOKUP($C64,'Pesticide Types'!$A$2:$A$519,'Pesticide Types'!$B$2:$B$519),"Unclassified") -> Insecticide | M64: =IFERROR(_xlfn.XLOOKUP($C64,'Pesticide Types'!$A$2:$A$519,'Pesticide Types'!$D$2:$D$519),"None") -> IRAC 6
A65: 240 - 2554 | B65: โปรวาโด เอ็กซ์ (Provado X) | C65: imidacloprid | D65: 60%W/V | E65: FS | F65: Bayer CropScience Pty Ltd. Australia | G65: ไบเออร์ไทย บจก. | H65: ไบเออร์ไทย บจก. | I65: ไบเออร์ไทย บจก. | J65: 06/12/2023 | K65: 05/12/2029 | L65: =IFERROR(_xlfn.XLOOKUP($C65,'Pesticide Types'!$A$2:$A$519,'Pesticide Types'!$B$2:$B$519),"Unclassified") -> Insecticide | M65: =IFERROR(_xlfn.XLOOKUP($C65,'Pesticide Types'!$A$2:$A$519,'Pesticide Types'!$D$2:$D$519),"None") -> IRAC 4A
A66: 241 - 2554 | B66: ซัน ไรซ์ (Sunrice) | C66: ethoxysulfuron | D66: 0.15 | E66: WG | F66: Bayer Vietnam Limited, Vietnam | G66: ไบเออร์ไทย บจก. | H66: ไบเออร์ไทย บจก. | I66: ไบเออร์ไทย บจก. | J66: 06/12/2023 | K66: 05/12/2029 | L66: =IFERROR(_xlfn.XLOOKUP($C66,'Pesticide Types'!$A$2:$A$519,'Pesticide Types'!$B$2:$B$519),"Unclassified") -> Herbicide | M66: =IFERROR(_xlfn.XLOOKUP($C66,'Pesticide Types'!$A$2:$A$519,'Pesticide Types'!$D$2:$D$519),"None") -> HRAC 2
A67: 243 - 2554 | B67: เพรทิลาคลอร์ เทค (Pretilachlor Tech.) | C67: pretilachlor | D67: 94%min. | E67: Tech. | F67: Deccan Fine Chemicals (India) Private Limited, India; Capital Industry Construction Technology Cp., Ltd. PRC; Hangzhou Nutrichem Co., Ltd. PRC | G67: ซินเจนทา ครอป โปรเทคชั่น บจก. | H67: ซินเจนทา ครอป โปรเทคชั่น บจก. | I67: ซินเจนทา ครอป โปรเทคชั่น บจก. | J67: 06/12/2023 | K67: 05/12/2029 | L67: =IFERROR(_xlfn.XLOOKUP($C67,'Pesticide Types'!$A$2:$A$519,'Pesticide Types'!$B$2:$B$519),"Unclassified") -> Herbicide | M67: =IFERROR(_xlfn.XLOOKUP($C67,'Pesticide Types'!$A$2:$A$519,'Pesticide Types'!$D$2:$D$519),"None") -> HRAC 15
A68: 245 - 2554 | B68: เคอร์บิกซ์ (Curbix) | C68: ethiprole | D68: 10%W/V | E68: SC | F68: Bayer CropScience (China) Co., Ltd. PRC ; Bayer CropScience K.K., Japan | G68: ไบเออร์ไทย บจก. | H68: ไบเออร์ไทย บจก. | I68: ไบเออร์ไทย บจก. | J68: 06/12/2023 | K68: 05/12/2029 | L68: =IFERROR(_xlfn.XLOOKUP($C68,'Pesticide Types'!$A$2:$A$519,'Pesticide Types'!$B$2:$B$519),"Unclassified") -> Insecticide | M68: =IFERROR(_xlfn.XLOOKUP($C68,'Pesticide Types'!$A$2:$A$519,'Pesticide Types'!$D$2:$D$519),"None") -> IRAC 2B
A69: 246 - 2554 | B69: เกาโช 70 ดับบลิวเอส (Gaucho 70 WS) | C69: imidacloprid | D69: 70%WS | E69: WS | F69: Bayer Vietnam Limited, vietnam | G69: ไบเออร์ไทย บจก. | H69: ไบเออร์ไทย บจก. | I69: ไบเออร์ไทย บจก. | J69: 06/12/2023 | K69: 05/12/2029 | L69: =IFERROR(_xlfn.XLOOKUP($C69,'Pesticide Types'!$A$2:$A$519,'Pesticide Types'!$B$2:$B$519),"Unclassified") -> Insecticide | M69: =IFERROR(_xlfn.XLOOKUP($C69,'Pesticide Types'!$A$2:$A$519,'Pesticide Types'!$D$2:$D$519),"None") -> IRAC 4A
A70: 247 - 2554 | B70: ทิลเลอร์ (Tiller) | C70: ethoxysulfuron+fenoxaprop-p-ethyl | D70: 2%+6.9%W/V | E70: SC | F70: Bayer Vietnam Limited, Vietnam | G70: ไบเออร์ไทย บจก. | H70: ไบเออร์ไทย บจก. | I70: ไบเออร์ไทย บจก. | J70: 06/12/2023 | K70: 05/12/2029 | L70: =IFERROR(_xlfn.XLOOKUP($C70,'Pesticide Types'!$A$2:$A$519,'Pesticide Types'!$B$2:$B$519),"Unclassified") -> Unclassified | M70: =IFERROR(_xlfn.XLOOKUP($C70,'Pesticide Types'!$A$2:$A$519,'Pesticide Types'!$D$2:$D$519),"None") -> None
A71: 253 - 2554 | B71: ทอร์ดอน (Tordon) | C71: 2,4-d-triisopropanolamine salt+picloram | D71: 45.2%+11.6%W/V | E71: SL | F71: PT. Corteva Agriscience Manufacturing Indonesia, Indonesia | G71: ดาว อะโกรไซแอนส์ (ประเทศไทย) บจก. | H71: ดาว อะโกรไซแอนส์ (ประเทศไทย) บจก. | I71: คอร์เทวา อะกริไซเอนซ์ (ประเทศไทย) บจก. | J71: 06/12/2023 | K71: 05/12/2029 | L71: =IFERROR(_xlfn.XLOOKUP($C71,'Pesticide Types'!$A$2:$A$519,'Pesticide Types'!$B$2:$B$519),"Unclassified") -> Unclassified | M71: =IFERROR(_xlfn.XLOOKUP($C71,'Pesticide Types'!$A$2:$A$519,'Pesticide Types'!$D$2:$D$519),"None") -> None
A72: 254 - 2554 | B72: อาเทีย | C72: cyproconazole+propiconazole | D72: 8%+25%W/V | E72: EC | F72: Syngenta Vietnam Ltd., Vietnam | G72: ซินเจนทา ครอป โปรเทคชั่น บจก. | H72: ซินเจนทา ครอป โปรเทคชั่น บจก. | I72: ซินเจนทา ครอป โปรเทคชั่น บจก. | J72: 06/12/2023 | K72: 05/12/2029 | L72: =IFERROR(_xlfn.XLOOKUP($C72,'Pesticide Types'!$A$2:$A$519,'Pesticide Types'!$B$2:$B$519),"Unclassified") -> Unclassified | M72: =IFERROR(_xlfn.XLOOKUP($C72,'Pesticide Types'!$A$2:$A$519,'Pesticide Types'!$D$2:$D$519),"None") -> None
A73: 256 - 2554 | B73: โซฟิต | C73: pretilachlor | D73: 30%W/V | E73: EC | F73: ซินเจนทา ครอป โปรเทคชั่น บจก. (นำเข้าสารเข้มข้นจาก Deccan Fine Chemicals (India) Private Limited, India; Capital Industry Construction Technology Co., Ltd., PRC; | G73: ซินเจนทา ครอป โปรเทคชั่น บจก. | H73: ซินเจนทา ครอป โปรเทคชั่น บจก. | I73: ซินเจนทา ครอป โปรเทคชั่น บจก. | J73: 06/12/2023 | K73: 05/12/2029 | L73: =IFERROR(_xlfn.XLOOKUP($C73,'Pesticide Types'!$A$2:$A$519,'Pesticide Types'!$B$2:$B$519),"Unclassified") -> Herbicide | M73: =IFERROR(_xlfn.XLOOKUP($C73,'Pesticide Types'!$A$2:$A$519,'Pesticide Types'!$D$2:$D$519),"None") -> HRAC 15
A74: 257 - 2554 | B74: สตาร์เรน (Starane) | C74: fluroxypyr-meptyl | D74: 28.8%W/V | E74: EC | F74: HPTa.n gCzohroteuv Na Autgrircihsceimen Cceo .M, Lantdu fPaRctCu)ring Indonesia, Indonesia | G74: คอร์เทวา อะกริไซเอนซ์ (ประเทศไทย) บจก. | H74: ดาว อะโกรไซแอนส์ (ประเทศไทย) บจก. | I74: คอร์เทวา อะกริไซเอนซ์ (ประเทศไทย) บจก. | J74: 06/12/2023 | K74: 05/12/2029 | L74: =IFERROR(_xlfn.XLOOKUP($C74,'Pesticide Types'!$A$2:$A$519,'Pesticide Types'!$B$2:$B$519),"Unclassified") -> Herbicide | M74: =IFERROR(_xlfn.XLOOKUP($C74,'Pesticide Types'!$A$2:$A$519,'Pesticide Types'!$D$2:$D$519),"None") -> HRAC 4
A75: 259 - 2554 | B75: ฟีโนแพ็ค (Fenopack) | C75: fenobucarb | D75: 50%W/V | E75: EC | F75: Yueyang Anda Chemicals Ltd. PRC | G75: เอเลฟองเต้ อโกรเคมิคอล บจก. | H75: เอเลฟองเต้ อโกรเคมีคอล | I75: ไอยราบรรจุภัณฑ์ บจก. | J75: 06/12/2023 | K75: 05/12/2029 | L75: =IFERROR(_xlfn.XLOOKUP($C75,'Pesticide Types'!$A$2:$A$519,'Pesticide Types'!$B$2:$B$519),"Unclassified") -> Insecticide | M75: =IFERROR(_xlfn.XLOOKUP($C75,'Pesticide Types'!$A$2:$A$519,'Pesticide Types'!$D$2:$D$519),"None") -> IRAC 1A
A76: 263 - 2554 | B76: อะซีโทคลอร์ 50 อีซี (Acetochlor 50 EC) | C76: acetochlor | D76: 50%W/V | E76: EC | F76: Shandong Weifang Rainbow Chemical Co., Ltd. PRC | G76: เจียไต๋ บจก. | H76: เจียไต๋ บจก. | I76: เจียไต๋ บจก. | J76: 06/12/2023 | K76: 05/12/2029 | L76: =IFERROR(_xlfn.XLOOKUP($C76,'Pesticide Types'!$A$2:$A$519,'Pesticide Types'!$B$2:$B$519),"Unclassified") -> Herbicide | M76: =IFERROR(_xlfn.XLOOKUP($C76,'Pesticide Types'!$A$2:$A$519,'Pesticide Types'!$D$2:$D$519),"None") -> HRAC 15
A77: 264 - 2554 | B77: บีม 75 ดับบลิวพี (Beam 75 WP) | C77: tricyclazole | D77: 0.75 | E77: WP | F77: Corteva Agriscience de Colombia S.AS., Colombia; Corteva Crop India Pvt. Ltd., India | G77: คอร์เทวา อะกริไซเอนซ์ (ประเทศไทย) บจก. | H77: ดาว อะโกรไซแอนส์ (ประเทศไทย) บจก. | I77: คอร์เทวา อะกริไซเอนซ์ (ประเทศไทย) บจก. | J77: 06/12/2023 | K77: 05/12/2029 | L77: =IFERROR(_xlfn.XLOOKUP($C77,'Pesticide Types'!$A$2:$A$519,'Pesticide Types'!$B$2:$B$519),"Unclassified") -> Fungicide | M77: =IFERROR(_xlfn.XLOOKUP($C77,'Pesticide Types'!$A$2:$A$519,'Pesticide Types'!$D$2:$D$519),"None") -> FRAC 16.1
A78: 265 - 2554 | B78: แดนทอ๊ซ (Dantosu) | C78: clothianidin | D78: 0.16 | E78: SG | F78: Sumitomo Chemical Co., Ltd. Japan | G78: ที.เจ.ซี. เคมี บจก. | H78: ที.เจ.ซี. เคมี บจก. | I78: ที.เจ.ซี. เคมี บจก. | J78: 06/12/2023 | K78: 05/12/2029 | L78: =IFERROR(_xlfn.XLOOKUP($C78,'Pesticide Types'!$A$2:$A$519,'Pesticide Types'!$B$2:$B$519),"Unclassified") -> Insecticide | M78: =IFERROR(_xlfn.XLOOKUP($C78,'Pesticide Types'!$A$2:$A$519,'Pesticide Types'!$D$2:$D$519),"None") -> IRAC 4A
A79: 272 - 2554 | B79: เคอร์บิกซ์ | C79: ethiprole | D79: 10%W/V | E79: SC | F79: Bayer CropScience (China) Co., Ltd. PRC ; Bayer CropScience K.K., Japan | G79: ไบเออร์ไทย บจก. | H79: ไบเออร์ไทย บจก. | I79: ไบเออร์ไทย บจก. | J79: 16/12/2023 | K79: 15/12/2029 | L79: =IFERROR(_xlfn.XLOOKUP($C79,'Pesticide Types'!$A$2:$A$519,'Pesticide Types'!$B$2:$B$519),"Unclassified") -> Insecticide | M79: =IFERROR(_xlfn.XLOOKUP($C79,'Pesticide Types'!$A$2:$A$519,'Pesticide Types'!$D$2:$D$519),"None") -> IRAC 2B
A80: 273 - 2554 | B80: โปรวาโด เอ็กซ์ | C80: imidacloprid | D80: 60%W/V | E80: FS | F80: Bayer CropScience Pty Ltd. Australia | G80: ไบเออร์ไทย บจก. | H80: ไบเออร์ไทย บจก. | I80: ไบเออร์ไทย บจก. | J80: 16/12/2023 | K80: 15/12/2029 | L80: =IFERROR(_xlfn.XLOOKUP($C80,'Pesticide Types'!$A$2:$A$519,'Pesticide Types'!$B$2:$B$519),"Unclassified") -> Insecticide | M80: =IFERROR(_xlfn.XLOOKUP($C80,'Pesticide Types'!$A$2:$A$519,'Pesticide Types'!$D$2:$D$519),"None") -> IRAC 4A
A81: 274 - 2554 | B81: แดนทอ๊ซ | C81: clothianidin | D81: 0.16 | E81: SG | F81: Sumitomo Chemical Co., Ltd. Japan | G81: ที.เจ.ซี. เคมี บจก. | H81: ที.เจ.ซี. เคมี บจก. | I81: ที.เจ.ซี. เคมี บจก. | J81: 19/12/2023 | K81: 18/12/2029 | L81: =IFERROR(_xlfn.XLOOKUP($C81,'Pesticide Types'!$A$2:$A$519,'Pesticide Types'!$B$2:$B$519),"Unclassified") -> Insecticide | M81: =IFERROR(_xlfn.XLOOKUP($C81,'Pesticide Types'!$A$2:$A$519,'Pesticide Types'!$D$2:$D$519),"None") -> IRAC 4A
A82: 275 - 2554 | B82: ฟลิ้นท์ | C82: trifloxystrobin | D82: 0.5 | E82: WG | F82: Bayer AG, Germany | G82: ไบเออร์ไทย บจก. | H82: ไบเออร์ไทย บจก. | I82: ไบเออร์ไทย บจก. | J82: 19/12/2023 | K82: 18/12/2029 | L82: =IFERROR(_xlfn.XLOOKUP($C82,'Pesticide Types'!$A$2:$A$519,'Pesticide Types'!$B$2:$B$519),"Unclassified") -> Fungicide | M82: =IFERROR(_xlfn.XLOOKUP($C82,'Pesticide Types'!$A$2:$A$519,'Pesticide Types'!$D$2:$D$519),"None") -> FRAC 11
A83: 276 - 2554 | B83: เกาโช 70 ดับบลิวเอส | C83: imidacloprid | D83: 70%WS | E83: WS | F83: Bayer Vietnam Limited, Vietnam | G83: ไบเออร์ไทย บจก. | H83: ไบเออร์ไทย บจก. | I83: ไบเออร์ไทย บจก. | J83: 19/12/2023 | K83: 18/12/2029 | L83: =IFERROR(_xlfn.XLOOKUP($C83,'Pesticide Types'!$A$2:$A$519,'Pesticide Types'!$B$2:$B$519),"Unclassified") -> Insecticide | M83: =IFERROR(_xlfn.XLOOKUP($C83,'Pesticide Types'!$A$2:$A$519,'Pesticide Types'!$D$2:$D$519),"None") -> IRAC 4A
A84: 278 - 2554 | B84: 2,4-ดี-โซเดียม (2,4-D-Sodium) | C84: 2,4-d-sodium | D84: 0.95 | E84: SP | F84: Shandong Weifang Rainbow Chemical Co., Ltd. PRC | G84: โกลบอล ครอปส์ บจก. | H84: โกลบอล ครอปส์ บจก. | I84: โกลบอล ครอปส์ บจก. | J84: 22/12/2023 | K84: 21/12/2029 | L84: =IFERROR(_xlfn.XLOOKUP($C84,'Pesticide Types'!$A$2:$A$519,'Pesticide Types'!$B$2:$B$519),"Unclassified") -> Herbicide | M84: =IFERROR(_xlfn.XLOOKUP($C84,'Pesticide Types'!$A$2:$A$519,'Pesticide Types'!$D$2:$D$519),"None") -> HRAC 4
A85: 279 - 2554 | B85: โอไมท้์ 30 (Omite 30) | C85: propargite | D85: 0.3 | E85: WP | F85: Eureka! Mfg Pty Ltd., Australia | G85: โซตัส อินเตอร์เนชั่นแนล บจก. | H85: โซตัส อินเตอร์เนชั่นแนล บจก. | I85: โซตัส อินเตอร์เนชั่นแนล บจก. | J85: 22/12/2023 | K85: 21/12/2029 | L85: =IFERROR(_xlfn.XLOOKUP($C85,'Pesticide Types'!$A$2:$A$519,'Pesticide Types'!$B$2:$B$519),"Unclassified") -> Acaricide | M85: =IFERROR(_xlfn.XLOOKUP($C85,'Pesticide Types'!$A$2:$A$519,'Pesticide Types'!$D$2:$D$519),"None") -> IRAC 12C
A86: 280 - 2554 | B86: ไกลโฟเซต-ไอโซโพรพิลแอมโมเนียม (Glyphosate-isopropylammonium) | C86: glyphosate-isopropylammonium | D86: 48%W/V | E86: SL | F86: Jingma Chemicals Co., Ltd. PRC. | G86: โปรเจ็ค ฟิลด์ บจก. | H86: โปรเจ็ค ฟิลด์ บจก. | I86: โปรเจ็ค ฟิลด์ บจก. | J86: 22/12/2023 | K86: 21/12/2029 | L86: =IFERROR(_xlfn.XLOOKUP($C86,'Pesticide Types'!$A$2:$A$519,'Pesticide Types'!$B$2:$B$519),"Unclassified") -> Herbicide | M86: =IFERROR(_xlfn.XLOOKUP($C86,'Pesticide Types'!$A$2:$A$519,'Pesticide Types'!$D$2:$D$519),"None") -> HRAC 9
A87: 281 - 2554 | B87: - | C87: 2,4-d-sodium | D87: 0.95 | E87: SP | F87: ADAMA Manufacturing Poland S.A., Poland | G87: ทีเอชซี อะโกรไซแอนส์ บจก. | H87: ทีเอชซี อะโกรไซแอนส์ บจก. | I87: ทีเอชซี อะโกรไซแอนส์ บจก. | J87: 22/12/2023 | K87: 21/12/2029 | L87: =IFERROR(_xlfn.XLOOKUP($C87,'Pesticide Types'!$A$2:$A$519,'Pesticide Types'!$B$2:$B$519),"Unclassified") -> Herbicide | M87: =IFERROR(_xlfn.XLOOKUP($C87,'Pesticide Types'!$A$2:$A$519,'Pesticide Types'!$D$2:$D$519),"None") -> HRAC 4
A88: 284 - 2554 | B88: เอพรอน เอ็กซ์แอล (Apron XL) | C88: metalaxyl-m | D88: 35%W/V | E88: ES | F88: Syngenta India Private Limited, India; Syngenta Espana, S.A., Spain | G88: ซินเจนทา ครอป โปรเทคชั่น บจก. | H88: ซินเจนทา ครอป โปรเทคชั่น บจก. | I88: ซินเจนทา ครอป โปรเทคชั่น บจก. | J88: 22/12/2023 | K88: 21/12/2029 | L88: =IFERROR(_xlfn.XLOOKUP($C88,'Pesticide Types'!$A$2:$A$519,'Pesticide Types'!$B$2:$B$519),"Unclassified") -> Fungicide | M88: =IFERROR(_xlfn.XLOOKUP($C88,'Pesticide Types'!$A$2:$A$519,'Pesticide Types'!$D$2:$D$519),"None") -> FRAC 4
A89: 286 - 2554 | B89: อะมีทรีน 80 % ดับบลิวพี (Ametryn 80 % WP) | C89: ametryn | D89: 0.8 | E89: WP | F89: Shandong Weifang Rainbow Chemical Co., Ltd. PRC | G89: เจียไต๋ บจก. | H89: เจียไต๋ บจก. | I89: เจียไต๋ บจก. | J89: 22/12/2023 | K89: 21/12/2029 | L89: =IFERROR(_xlfn.XLOOKUP($C89,'Pesticide Types'!$A$2:$A$519,'Pesticide Types'!$B$2:$B$519),"Unclassified") -> Herbicide | M89: =IFERROR(_xlfn.XLOOKUP($C89,'Pesticide Types'!$A$2:$A$519,'Pesticide Types'!$D$2:$D$519),"None") -> HRAC 5
A90: 287 - 2554 | B90: อิมิดาโคลพริด (IMIDACLOPRID) | C90: imidacloprid | D90: 0.7 | E90: WG | F90: Anhui Huaxing Chemical Industry Co., Ltd. PRC | G90: แอ็กโกร (ประเทศไทย) บจก. | H90: แอ็กโกร (ประเทศไทย) บจก. | I90: แอ็กโกร (ประเทศไทย) บจก. | J90: 22/12/2023 | K90: 21/12/2029 | L90: =IFERROR(_xlfn.XLOOKUP($C90,'Pesticide Types'!$A$2:$A$519,'Pesticide Types'!$B$2:$B$519),"Unclassified") -> Insecticide | M90: =IFERROR(_xlfn.XLOOKUP($C90,'Pesticide Types'!$A$2:$A$519,'Pesticide Types'!$D$2:$D$519),"None") -> IRAC 4A
A91: 289 - 2554 | B91: อะมีทรีน 80 ดับบลิวพี (Ametryn 80 WP) | C91: ametryn | D91: 0.8 | E91: WP | F91: Shandong Weifang Rainbow Chemical Co., Ltd. PRC | G91: โกลบอล ครอปส์ บจก. | H91: โกลบอล ครอปส์ บจก. | I91: โกลบอล ครอปส์ บจก. | J91: 22/12/2023 | K91: 21/12/2029 | L91: =IFERROR(_xlfn.XLOOKUP($C91,'Pesticide Types'!$A$2:$A$519,'Pesticide Types'!$B$2:$B$519),"Unclassified") -> Herbicide | M91: =IFERROR(_xlfn.XLOOKUP($C91,'Pesticide Types'!$A$2:$A$519,'Pesticide Types'!$D$2:$D$519),"None") -> HRAC 5
A92: 290 - 2554 | B92: คาร์แทป 50 เอสพี (Cartap 50 SP) | C92: cartap hydrochloride | D92: 0.5 | E92: SP | F92: Jiangsu Tianrong Group Co., Ltd. PRC | G92: โกลบอล ครอปส์ บจก. | H92: โกลบอล ครอปส์ บจก. | I92: โกลบอล ครอปส์ บจก. | J92: 22/12/2023 | K92: 21/12/2029 | L92: =IFERROR(_xlfn.XLOOKUP($C92,'Pesticide Types'!$A$2:$A$519,'Pesticide Types'!$B$2:$B$519),"Unclassified") -> Insecticide | M92: =IFERROR(_xlfn.XLOOKUP($C92,'Pesticide Types'!$A$2:$A$519,'Pesticide Types'!$D$2:$D$519),"None") -> IRAC 14
A93: 293 - 2554 | B93: ซิมเมอร์ (ZIMMER) | C93: 2,4-d-dimethylammonium | D93: 84%W/V | E93: SL | F93: Shandong Weifang Rainbow Chemical Co., Ltd. PRC | G93: ไอ ซี พี ลัดดา อินเตอร์เทรด บจก. | H93: ไอ ซี พี ลัดดา อินเตอร์เทรด บจก. | I93: ไอ ซี พี ลัดดา อินเตอร์เทรด บจก. | J93: 22/12/2023 | K93: 21/12/2029 | L93: =IFERROR(_xlfn.XLOOKUP($C93,'Pesticide Types'!$A$2:$A$519,'Pesticide Types'!$B$2:$B$519),"Unclassified") -> Herbicide | M93: =IFERROR(_xlfn.XLOOKUP($C93,'Pesticide Types'!$A$2:$A$519,'Pesticide Types'!$D$2:$D$519),"None") -> HRAC 4
A94: 295 - 2554 | B94: โซฟิต (Sofit) | C94: pretilachlor | D94: 30%W/V | E94: EC | F94: Asiatic Agricultural Industries Pte., Ltd., Singapore; Syngenta Vietnam Ltd., Vietnam | G94: ซินเจนทา ครอป โปรเทคชั่น บจก. | H94: ซินเจนทา ครอป โปรเทคชั่น บจก. | I94: ซินเจนทา ครอป โปรเทคชั่น บจก. | J94: 22/12/2023 | K94: 21/12/2029 | L94: =IFERROR(_xlfn.XLOOKUP($C94,'Pesticide Types'!$A$2:$A$519,'Pesticide Types'!$B$2:$B$519),"Unclassified") -> Herbicide | M94: =IFERROR(_xlfn.XLOOKUP($C94,'Pesticide Types'!$A$2:$A$519,'Pesticide Types'!$D$2:$D$519),"None") -> HRAC 15
A95: 305 - 2554 | B95: แมนโคเซบ 80% ดับบลิวพี (Mancozeb 80% WP) | C95: mancozeb | D95: 0.8 | E95: WP | F95: Limin Chemical Co., Ltd. PRC | G95: เอราวัณ เคมีเกษตร บจก. | H95: เอราวัณ เคมีเกษตร บจก. | I95: เอราวัณ เคมีเกษตร บจก. | J95: 22/12/2023 | K95: 21/12/2029 | L95: =IFERROR(_xlfn.XLOOKUP($C95,'Pesticide Types'!$A$2:$A$519,'Pesticide Types'!$B$2:$B$519),"Unclassified") -> Fungicide | M95: =IFERROR(_xlfn.XLOOKUP($C95,'Pesticide Types'!$A$2:$A$519,'Pesticide Types'!$D$2:$D$519),"None") -> FRAC M03
A96: 306 - 2554 | B96: อะมีทรีน 50% เอสซี (Ametryn 50% SC) | C96: ametryn | D96: 50%W/V | E96: SC | F96: Zhejiang Zhongshan Chemical Industry Group Co., Ltd. PRC | G96: เอราวัณ เคมีเกษตร บจก. | H96: เอราวัณ เคมีเกษตร บจก. | I96: เอราวัณ เคมีเกษตร บจก. | J96: 22/12/2023 | K96: 21/12/2029 | L96: =IFERROR(_xlfn.XLOOKUP($C96,'Pesticide Types'!$A$2:$A$519,'Pesticide Types'!$B$2:$B$519),"Unclassified") -> Herbicide | M96: =IFERROR(_xlfn.XLOOKUP($C96,'Pesticide Types'!$A$2:$A$519,'Pesticide Types'!$D$2:$D$519),"None") -> HRAC 5
A97: 307 - 2554 | B97: อะทราซีน 500 กรัม/ลิตร เอสซี (Atrazine 500 g/l SC) | C97: atrazine | D97: 50%W/V | E97: SC | F97: Zhejiang Zhongshan Chemical Industry Group Co., Ltd. PRC | G97: เอราวัณ เคมีเกษตร บจก. | H97: เอราวัณ เคมีเกษตร บจก. | I97: คชา เคมีการเกษตร บจก. | J97: 22/12/2023 | K97: 21/12/2029 | L97: =IFERROR(_xlfn.XLOOKUP($C97,'Pesticide Types'!$A$2:$A$519,'Pesticide Types'!$B$2:$B$519),"Unclassified") -> Herbicide | M97: =IFERROR(_xlfn.XLOOKUP($C97,'Pesticide Types'!$A$2:$A$519,'Pesticide Types'!$D$2:$D$519),"None") -> HRAC 5
A98: 308 - 2554 | B98: อะทราซีน 80% ดับบลิวพี (Atrazine 80% WP) | C98: atrazine | D98: 0.8 | E98: WP | F98: Zhejiang Zhongshan Chemical Industry Group Co., Ltd. PRC | G98: เอราวัณ เคมีเกษตร บจก. | H98: เอราวัณ เคมีเกษตร บจก. | I98: เอราวัณ เคมีเกษตร บจก. | J98: 22/12/2023 | K98: 22/12/2029 | L98: =IFERROR(_xlfn.XLOOKUP($C98,'Pesticide Types'!$A$2:$A$519,'Pesticide Types'!$B$2:$B$519),"Unclassified") -> Herbicide | M98: =IFERROR(_xlfn.XLOOKUP($C98,'Pesticide Types'!$A$2:$A$519,'Pesticide Types'!$D$2:$D$519),"None") -> HRAC 5
A99: 309 - 2554 | B99: อะซีโทคลอร์ 500 กรัม/ลิตร อีซี (Acetochlor 500 g/l EC) | C99: acetochlor | D99: 50%W/V | E99: EC | F99: Nantong Jiangshan Agrochemical & Chemicals Limited Liability Co. PRC | G99: เอราวัณ เคมีเกษตร บจก. | H99: เอราวัณ เคมีเกษตร บจก. | I99: เอราวัณ เคมีเกษตร บจก. | J99: 23/12/2023 | K99: 22/12/2029 | L99: =IFERROR(_xlfn.XLOOKUP($C99,'Pesticide Types'!$A$2:$A$519,'Pesticide Types'!$B$2:$B$519),"Unclassified") -> Herbicide | M99: =IFERROR(_xlfn.XLOOKUP($C99,'Pesticide Types'!$A$2:$A$519,'Pesticide Types'!$D$2:$D$519),"None") -> HRAC 15
A100: 328 - 2554 | B100: ไกลโฟเซต ไอพีเอ 480 กรัม/ลิตร เอสแอล (Glyphosate IPA 480 g/l SL) | C100: glyphosate-isopropylammonium | D100: 48%W/V | E100: SL | F100: Nantong Jiangshan Agrochemical & Chemicals Limited Liability Co. PRC | G100: เอราวัณ เคมีเกษตร บจก. | H100: เอราวัณ เคมีเกษตร บจก. | I100: เอราวัณ เคมีเกษตร บจก. | J100: 28/12/2023 | K100: 27/12/2029 | L100: =IFERROR(_xlfn.XLOOKUP($C100,'Pesticide Types'!$A$2:$A$519,'Pesticide Types'!$B$2:$B$519),"Unclassified") -> Herbicide | M100: =IFERROR(_xlfn.XLOOKUP($C100,'Pesticide Types'!$A$2:$A$519,'Pesticide Types'!$D$2:$D$519),"None") -> HRAC 9
...

Sheet Pesticide Types
A1: Active Ingredient (common_name) | B1: Pesticide Type | C1: Rows in Registration | D1: MoA Group (HRAC/IRAC/FRAC)
A2: imidacloprid | B2: Insecticide | C2: 485 | D2: IRAC 4A
A3: glufosinate-ammonium | B3: Herbicide | C3: 483 | D3: HRAC 10
A4: emamectin benzoate | B4: Insecticide | C4: 482 | D4: IRAC 6
A5: glyphosate-isopropylammonium | B5: Herbicide | C5: 463 | D5: HRAC 9
A6: fipronil | B6: Insecticide | C6: 440 | D6: IRAC 2B
A7: butachlor | B7: Herbicide | C7: 401 | D7: HRAC 15
A8: abamectin | B8: Insecticide | C8: 382 | D8: IRAC 6
A9: ametryn | B9: Herbicide | C9: 364 | D9: HRAC 5
A10: atrazine | B10: Herbicide | C10: 361 | D10: HRAC 5
A11: carbendazim | B11: Fungicide | C11: 340 | D11: FRAC 1
A12: diuron | B12: Herbicide | C12: 325 | D12: HRAC 5
A13: bispyribac-sodium | B13: Herbicide | C13: 322 | D13: HRAC 2
... A519: flufenacet + metribuzin | B519: Herbicide | C519: 1 | D519: HRAC 15 + 5
